cmdbench/__init__.py
cmdbench/cli.py
cmdbench/core.py
cmdbench/keys_dict.py
cmdbench/result.py
cmdbench/utils.py
cmdbench-0.1.22.dist-info/LICENSE
cmdbench-0.1.22.dist-info/METADATA
cmdbench-0.1.22.dist-info/WHEEL
cmdbench-0.1.22.dist-info/entry_points.txt
cmdbench-0.1.22.dist-info/RECORD
