Metadata-Version: 2.1
Name: cmdbench
Version: 0.1.22
Summary: Quick and easy benchmarking for any command's CPU, memory, disk usage and runtime.
Home-page: https://github.com/manzik/cmdbench
License: MIT
Keywords: benchmarks,benchmark,benchmarking,profiler,profiling,timeit,time,runtime,performance,monitoring,monitor,cpu,memory,ram,disk
Author: Mohsen Yousefian
Author-email: contact@manzik.com
Requires-Python: >=3.6
Classifier: Development Status :: 4 - Beta
Classifier: Intended Audience :: Developers
Classifier: Intended Audience :: End Users/Desktop
Classifier: Intended Audience :: Information Technology
Classifier: Intended Audience :: Science/Research
Classifier: License :: OSI Approved :: MIT License
Classifier: Operating System :: MacOS
Classifier: Operating System :: Microsoft :: Windows
Classifier: Operating System :: POSIX
Classifier: Operating System :: Unix
Classifier: Programming Language :: Python :: 3
Classifier: Programming Language :: Python :: 3.6
Classifier: Programming Language :: Python :: 3.7
Classifier: Programming Language :: Python :: 3.8
Classifier: Programming Language :: Python :: 3.9
Classifier: Programming Language :: Python :: 3.10
Classifier: Programming Language :: Python :: 3.11
Classifier: Programming Language :: Python :: 3.12
Classifier: Programming Language :: Python :: 3.13
Classifier: Topic :: Software Development :: Testing
Classifier: Topic :: System :: Benchmark
Classifier: Topic :: Utilities
Requires-Dist: Click
Requires-Dist: beeprint (>=2.4.10)
Requires-Dist: colorama
Requires-Dist: matplotlib (>=3.3.3)
Requires-Dist: numpy
Requires-Dist: psutil (>=5.7.0)
Requires-Dist: scipy (>=1.5.0)
Requires-Dist: tqdm
Project-URL: Repository, https://github.com/manzik/cmdbench
